README.md
setup.py
testreportng/__init__.py
testreportng/case.py
testreportng/constants.py
testreportng/detail.py
testreportng/result.py
testreportng/suite.py
testreportng/utils.py
testreportng.egg-info/PKG-INFO
testreportng.egg-info/SOURCES.txt
testreportng.egg-info/dependency_links.txt
testreportng.egg-info/requires.txt
testreportng.egg-info/top_level.txt
testreportng/ext/__init__.py
testreportng/ext/html.py