Metadata-Version: 2.1
Name: testreportng
Version: 0.3.0
Summary: next generation of test report, for unittest
Home-page: https://github.com/williamfzc/testreportng
Author: williamfzc
Author-email: fengzc@vip.qq.com
License: MIT
Platform: UNKNOWN
Classifier: License :: OSI Approved :: MIT License
Classifier: Programming Language :: Python
Classifier: Programming Language :: Python :: 3
Provides-Extra: html
